Metadata-Version: 1.1
Name: django-protractor-new
Version: 0.9.1
Summary: Easily integrate your protractor tests with django
Home-page: UNKNOWN
Author: Jared Hellman (formerly James Pulec)
Author-email: jhellma1@gmail.com
License: MIT License
Platform: UNKNOWN
Classifier: Environment :: Web Environment
Classifier: Framework :: Django
Classifier: Intended Audience :: Developers
Classifier: Operating System :: OS Independent
Classifier: Programming Language :: Python
Classifier: Programming Language :: Python :: 2
Classifier: Programming Language :: Python :: 3
